github3api/__init__.py
github3api/githubapi.py
github3api-0.3.2.dist-info/METADATA
github3api-0.3.2.dist-info/WHEEL
github3api-0.3.2.dist-info/namespace_packages.txt
github3api-0.3.2.dist-info/top_level.txt
github3api-0.3.2.dist-info/zip-safe
github3api-0.3.2.dist-info/RECORD
